Willthon/GAN_test/layer1_discriminator.v
module layer1_discriminator (
    input wire clk,
    input wire rst,
    input wire start,
    // Verilog-2001 compatible: flatten 256 x 16-bit inputs into one packed vector
    // Each input element is Q8.8 (16 bits). Total width = 16 * 256 = 4096 bits
    input wire signed [16*256-1:0] flat_input, // flattened input bus (MSB first)
    output reg signed [15:0] score_out,            // Output Skor Logit (Q8.8)
    output reg decision_real,                      // 1 = Real, 0 = Fake
    output reg done                                // High when result is ready
);

    // ==========================================
    // Memory Parameters
    // ==========================================
    reg signed [15:0] weights_mem [0:255]; // 256 Bobot (1 per input)
    reg signed [15:0] bias_mem [0:0];      // 1 Bias saja untuk output node

    initial begin
        // Load file hex yang dibuat oleh Python
        $readmemh("disc_weights.hex", weights_mem);
        $readmemh("disc_biases.hex", bias_mem);
    end

    // ==========================================
    // Perhitungan Neural Network
    // ==========================================
    integer i;
    reg signed [31:0] accumulator; // 32-bit agar tidak overflow saat penjumlahan
    reg signed [31:0] bias_shifted;
    // compute product combinationally for the current index to avoid register update races
    wire signed [15:0] slice_w;
    wire signed [31:0] current_product;
    reg signed [31:0] next_acc;
    reg [7:0] idx;                 // 0..255
    reg busy;
    
    // slice and product wires
    assign slice_w = $signed(flat_input[(idx+1)*16-1 -: 16]);
    assign current_product = $signed(slice_w) * $signed(weights_mem[idx]);

    // Sequential MAC pipeline: perform one multiply-accumulate per clock
    // Protocol: assert `start` for one cycle. Module loads bias, then performs
    // 256 MAC cycles; when done, `done` is asserted and `score_out`/`decision_real` are valid.
    always @(posedge clk or posedge rst) begin
        if (rst) begin
            accumulator <= 32'sd0;
            bias_shifted <= 32'sd0;
            next_acc <= 32'sd0;
            idx <= 8'd0;
            busy <= 1'b0;
            done <= 1'b0;
            score_out <= 16'sd0;
            decision_real <= 1'b0;
        end else begin
            if (start && !busy) begin
                // Start a new MAC run: load bias and begin from index 0
                bias_shifted <= $signed(bias_mem[0]) <<< 8;
                accumulator <= $signed(bias_mem[0]) <<< 8;
                idx <= 8'd0;
                busy <= 1'b1;
                done <= 1'b0;
            end else if (busy) begin
                // Compute product for current index (combinational) and accumulate
                // Note: `current_product` uses the current `idx` value (from previous cycle),
                // which is the intended behavior for one MAC per clock.
                // next_acc is a combinational expression of the current accumulator and product
                // so we can update accumulator and drive outputs based on it.
                next_acc = accumulator + current_product;
                accumulator <= next_acc;

                if (idx == 8'd255) begin
                    // Last element processed this cycle; produce outputs using next_acc
                    score_out <= next_acc[23:8];
                    decision_real <= (next_acc > 0) ? 1'b1 : 1'b0;
                    busy <= 1'b0;
                    done <= 1'b1;
                end

                idx <= idx + 1'b1;
            end else begin
                // idle: clear done after one cycle so user can pulse start again
                if (done)
                    done <= 1'b0;
            end
        end
    end

endmodule

Willthon/GAN_test/layer1_discriminator_tb.v
`timescale 1ns / 1ps

module layer1_discriminator_tb;

    // Inputs
    reg signed [15:0] inputs [0:255]; // Array input 256 elemen
    // Flattened bus to connect to DUT (16 bits per element)
    reg signed [16*256-1:0] flat_input;
    reg clk;
    reg rst;
    reg start;

    // Outputs
    wire signed [15:0] score_out;
    wire decision_real;
    wire done;

    // Instantiate Unit Under Test (UUT)
    layer1_discriminator uut (
        .clk(clk),
        .rst(rst),
        .start(start),
        .flat_input(flat_input), 
        .score_out(score_out), 
        .decision_real(decision_real),
        .done(done)
    );

    // Keep the flattened bus updated from the array inputs
    integer i_pack;
    always @(*) begin
        for (i_pack = 0; i_pack < 256; i_pack = i_pack + 1) begin
            flat_input[(i_pack+1)*16-1 -: 16] = inputs[i_pack];
        end
    end

    // Helper untuk konversi tampilan float
    function real q8_8_to_real;
        input signed [15:0] val;
        begin
            q8_8_to_real = val / 256.0;
        end
    endfunction


    integer k;

    // Clock generator: 10ns period
    initial begin
        clk = 0;
        forever #5 clk = ~clk;
    end

    initial begin
        $dumpfile("discriminator_test.vcd");
        $dumpvars(0, layer1_discriminator_tb);

        // Reset and init
        rst = 1;
        start = 0;
        #20;
        rst = 0;

        // 1. Load Input Test Vector dari file Hex
        // (Ini mensimulasikan data yang masuk dari Generator)
        $readmemh("disc_input_test.hex", inputs);

        $display("--------------------------------------------------");
        $display("   TESTING DISCRIMINATOR (LAYER 1) ");
        $display("--------------------------------------------------");
        
        // Tampilkan beberapa input sampel
        $display("Sample Inputs (first 5): %f, %f, %f, %f, %f", 
                 q8_8_to_real(inputs[0]), q8_8_to_real(inputs[1]), 
                 q8_8_to_real(inputs[2]), q8_8_to_real(inputs[3]), 
                 q8_8_to_real(inputs[4]));

        // Pulse start for one clock to begin MAC
        @(posedge clk);
        start = 1;
        @(posedge clk);
        start = 0;

        // Wait for done
        wait(done == 1);
        #1; // small delta to let outputs settle

        // 2. Cek Output
        $display("--------------------------------------------------");
        $display("OUTPUT RESULT:");
        $display("Raw Hex Score : %h", score_out);
        $display("Real Score    : %f", q8_8_to_real(score_out));
        $display("Decision      : %b (1=REAL, 0=FAKE)", decision_real);
        $display("--------------------------------------------------");

        // Test Case 2: Input Zero (Harus hanya keluar Bias)
        $display("\nTest Case 2: Zero Inputs");
        for (k=0; k<256; k=k+1) inputs[k] = 16'd0;

        // start again
        @(posedge clk);
        start = 1;
        @(posedge clk);
        start = 0;
        wait(done == 1);
        #1;
        $display("Score (Bias only) : %f", q8_8_to_real(score_out));

        $finish;
    end

endmodule

Willthon/GAN_test/discriminator_test.vcd
$date
	Tue Nov 25 13:34:00 2025
$end
$version
	Icarus Verilog
$end
$timescale
	1ps
$end
$scope module layer1_discriminator_tb $end
$var wire 16 ! score_out [15:0] $end
$var wire 1 " done $end
$var wire 1 # decision_real $end
$var reg 1 $ clk $end
$var reg 4096 % flat_input [4095:0] $end
$var reg 1 & rst $end
$var reg 1 ' start $end
$var integer 32 ( i_pack [31:0] $end
$var integer 32 ) k [31:0] $end
$scope function q8_8_to_real $end
$var reg 16 * val [15:0] $end
$upscope $end
$scope module uut $end
$var wire 1 $ clk $end
$var wire 4096 + flat_input [4095:0] $end
$var wire 1 & rst $end
$var wire 1 ' start $end
$var wire 16 , slice_w [15:0] $end
$var wire 32 - current_product [31:0] $end
$var reg 32 . accumulator [31:0] $end
$var reg 32 / bias_shifted [31:0] $end
$var reg 1 0 busy $end
$var reg 1 # decision_real $end
$var reg 1 " done $end
$var reg 8 1 idx [7:0] $end
$var reg 32 2 next_acc [31:0] $end
$var reg 16 3 score_out [15:0] $end
$upscope $end
$upscope $end
$enddefinitions $end
$comment Show the parameter values. $end
$dumpall
$end
#0
$dumpvars
b0 3
b0 2
b0 1
00
b0 /
b0 .
bx -
bx ,
bx +
bx *
bx )
bx (
0'
1&
bx %
0$
0#
0"
b0 !
$end
#5000
1$
#10000
0$
#15000
1$
#20000
b11111111111111111101011101100101 -
b1111111110011101 ,
b1111111110000010000000001011100111111111100010000000000011001000000000000100111111111111001010000000000001100111111111111111100011111111111100101111111110001001000000001101100100000000111000001111111100101111111111111100101011111111100110000000000000110101000000001111011100000000101000001111111100101100111111111010111100000000111110010000000001000101111111111111101011111111101000001111111110100000111111110100000000000000010011001111111110001010111111110001111000000000101101110000000011010111000000000001011100000000101111000000000010100011000000000111001011111111101100100000000011110100000000000010000011111111000111100000000000000010111111111011101100000000111011111111111100000001000000001000101011111111110000111111111111111011111111111010000000000000101000000000000011001110111111111110001011111111000111101111111110111010000000000011110111111111100111101111111101000000000000001111001000000000111100100000000001001000111111111111011000000000011111110000000010000011111111111001111100000000100010010000000001111110111111110010000100000000011011100000000010111000111111110000110111111111011001001111111111000000000000001001000111111111101000100000000011110110000000000100101000000000001111111111111111100101111111111001001000000000011001000000000000111001111111110110111100000000111010010000000000011101111111111111011000000000001000110000000000100111000000001010011111111111001110000000000011010100111111111001100100000000011010000000000000000101000000000101011100000000010001001111111100100100000000001110010000000000001110010000000000000011000000000000100111111111111110100000000001100001111111110001100100000000100111110000000000001111111111111011000100000000101111101111111111001110111111110001001100000000010001111111111111100010111111110111111000000000100111101111111111000101000000000000010000000000101001111111111110111100111111111111010100000000111010100000000011001000000000001010110011111111100101010000000010010000000000000101111000000000000101010000000010111100111111110001110000000000100011000000000001011111111111111110001011111111101100111111111111110101000000001011001111111111000001001111111110100011111111111111101100000000110101110000000011100101111111111111101011111111100000001111111111111100111111110100111100000000111011011111111111000001111111111001101011111111101100011111111100110001000000000011000011111111110000001111111111001101111111111001010000000000000001110000000001111111000000000110111100000000001110001111111101000100000000001110001111111111101111101111111110110111111111111100010000000000110000000000000010001000111111110111010111111111000101111111111101010011111111110101000111111111110010100000000011100100000000000010010100000000111010101111111100000111000000000011010111111111111000101111111111110010000000000000110000000000000110001111111101111010000000001011111100000000000101000000000001101011000000000011110000000000100101010000000000101001111111110110001100000000001100111111111101111010000000000101101000000000001111100000000001010011111111110000101011111111110110111111111100110000111111111100110100000000111111111111111101000111111111111101110111111111100010100000000001110111000000001111100000000000100010000000000001001101000000001000011000000000000000000000000001000101000000001101110100000000101101111111111110011011111111111001100111111111100100011111111110001010111111111101101011111111010000100000000011001100000000001100101111111111101011010000000001101000111111110010101111111111010000000000000000001111000000000101011111111111001011001111111111100000111111110011100100000000100110010000000011000101111111111011100000000000101001010000000001001000111111110000010011111111000101101111111101000011000000001000101011111111101111101111111111010101000000000111011111111111011110111111111111110100111111110101100111111111111111110000000011000111000000000011010100000000010010000000000010110110111111111101000000000000101101001111111101011110000000001100010100000000111101010000000000111001000000001111001111111111000001010000000000101011111111111101001011111111011101000000000000011110111111110011100000000000011110111111111110011101 %
b1111111110000010000000001011100111111111100010000000000011001000000000000100111111111111001010000000000001100111111111111111100011111111111100101111111110001001000000001101100100000000111000001111111100101111111111111100101011111111100110000000000000110101000000001111011100000000101000001111111100101100111111111010111100000000111110010000000001000101111111111111101011111111101000001111111110100000111111110100000000000000010011001111111110001010111111110001111000000000101101110000000011010111000000000001011100000000101111000000000010100011000000000111001011111111101100100000000011110100000000000010000011111111000111100000000000000010111111111011101100000000111011111111111100000001000000001000101011111111110000111111111111111011111111111010000000000000101000000000000011001110111111111110001011111111000111101111111110111010000000000011110111111111100111101111111101000000000000001111001000000000111100100000000001001000111111111111011000000000011111110000000010000011111111111001111100000000100010010000000001111110111111110010000100000000011011100000000010111000111111110000110111111111011001001111111111000000000000001001000111111111101000100000000011110110000000000100101000000000001111111111111111100101111111111001001000000000011001000000000000111001111111110110111100000000111010010000000000011101111111111111011000000000001000110000000000100111000000001010011111111111001110000000000011010100111111111001100100000000011010000000000000000101000000000101011100000000010001001111111100100100000000001110010000000000001110010000000000000011000000000000100111111111111110100000000001100001111111110001100100000000100111110000000000001111111111111011000100000000101111101111111111001110111111110001001100000000010001111111111111100010111111110111111000000000100111101111111111000101000000000000010000000000101001111111111110111100111111111111010100000000111010100000000011001000000000001010110011111111100101010000000010010000000000000101111000000000000101010000000010111100111111110001110000000000100011000000000001011111111111111110001011111111101100111111111111110101000000001011001111111111000001001111111110100011111111111111101100000000110101110000000011100101111111111111101011111111100000001111111111111100111111110100111100000000111011011111111111000001111111111001101011111111101100011111111100110001000000000011000011111111110000001111111111001101111111111001010000000000000001110000000001111111000000000110111100000000001110001111111101000100000000001110001111111111101111101111111110110111111111111100010000000000110000000000000010001000111111110111010111111111000101111111111101010011111111110101000111111111110010100000000011100100000000000010010100000000111010101111111100000111000000000011010111111111111000101111111111110010000000000000110000000000000110001111111101111010000000001011111100000000000101000000000001101011000000000011110000000000100101010000000000101001111111110110001100000000001100111111111101111010000000000101101000000000001111100000000001010011111111110000101011111111110110111111111100110000111111111100110100000000111111111111111101000111111111111101110111111111100010100000000001110111000000001111100000000000100010000000000001001101000000001000011000000000000000000000000001000101000000001101110100000000101101111111111110011011111111111001100111111111100100011111111110001010111111111101101011111111010000100000000011001100000000001100101111111111101011010000000001101000111111110010101111111111010000000000000000001111000000000101011111111111001011001111111111100000111111110011100100000000100110010000000011000101111111111011100000000000101001010000000001001000111111110000010011111111000101101111111101000011000000001000101011111111101111101111111111010101000000000111011111111111011110111111111111110100111111110101100111111111111111110000000011000111000000000011010100000000010010000000000010110110111111111101000000000000101101001111111101011110000000001100010100000000111101010000000000111001000000001111001111111111000001010000000000101011111111111101001011111111011101000000000000011110111111110011100000000000011110111111111110011101 +
b100000000 (
0$
b1111111101110100 *
0&
#25000
10
b11111111111111111000011100000000 .
b11111111111111111000011100000000 /
1'
1$
#30000
0$
#35000
b1111011 ,
b11111111111111111100101010101011 -
b1 1
b11111111111111110101111001100101 .
b11111111111111110101111001100101 2
0'
1$
#40000
0$
#45000
b1111111100111000 ,
b11111111111111111100011011111000 -
b10 1
b11111111111111110010100100010000 .
b11111111111111110010100100010000 2
1$
#50000
0$
#55000
b11110 ,
b11111111111111111111010101110100 -
b11 1
b11111111111111101111000000001000 .
b11111111111111101111000000001000 2
1$
#60000
0$
#65000
b1111111101110100 ,
b100010001011100 -
b100 1
b11111111111111101110010101111100 .
b11111111111111101110010101111100 2
1$
#70000
0$
#75000
b1111111111010010 ,
b110101001100 -
b101 1
b11111111111111110010100111011000 .
b11111111111111110010100111011000 2
1$
#80000
0$
#85000
b101011 ,
b11111111111111111111101101110111 -
b110 1
b11111111111111110011011100100100 .
b11111111111111110011011100100100 2
1$
#90000
0$
#95000
b1111111100000101 ,
b1111101100 -
b111 1
b11111111111111110011001010011011 .
b11111111111111110011001010011011 2
1$
#100000
0$
#105000
b11110011 ,
b11110011000 -
b1000 1
b11111111111111110011011010000111 .
b11111111111111110011011010000111 2
1$
#110000
0$
#115000
b111001 ,
b11111111111111111110111110000110 -
b1001 1
b11111111111111110011111000011111 .
b11111111111111110011111000011111 2
1$
#120000
0$
#125000
b11110101 ,
b1110110101011 -
b1010 1
b11111111111111110010110110100101 .
b11111111111111110010110110100101 2
1$
#130000
0$
#135000
b11000101 ,
b10100011001001 -
b1011 1
b11111111111111110100101101010000 .
b11111111111111110100101101010000 2
1$
#140000
0$
#145000
b1111111101011110 ,
b100001001110010 -
b1100 1
b11111111111111110111010000011001 .
b11111111111111110111010000011001 2
1$
#150000
0$
#155000
b10110100 ,
b11111111111111111011111101010000 -
b1101 1
b11111111111111111011011010001011 .
b11111111111111111011011010001011 2
1$
#160000
0$
#165000
b1111111111010000 ,
b11111111111111111110111110110000 -
b1110 1
b11111111111111110111010111011011 .
b11111111111111110111010111011011 2
1$
#170000
0$
#175000
b10110110 ,
b100000101101000 -
b1111 1
b11111111111111110110010110001011 .
b11111111111111110110010110001011 2
1$
#180000
0$
#185000
b1001000 ,
b11111111111111111110100100111000 -
b10000 1
b11111111111111111010011011110011 .
b11111111111111111010011011110011 2
1$
#190000
0$
#195000
b110101 ,
b11110101001 -
b10001 1
b11111111111111111001000000101011 .
b11111111111111111001000000101011 2
1$
#200000
0$
#205000
b11000111 ,
b11111111111111111010010001000110 -
b10010 1
b11111111111111111001011111010100 .
b11111111111111111001011111010100 2
1$
#210000
0$
#215000
b1111111111111111 ,
b1010101 -
b10011 1
b11111111111111110011110000011010 .
b11111111111111110011110000011010 2
1$
#220000
0$
#225000
b1111111101011001 ,
b11111111111111111011001001011111 -
b10100 1
b11111111111111110011110001101111 .
b11111111111111110011110001101111 2
1$
#230000
0$
#235000
b1111111111110100 ,
b10000111000 -
b10101 1
b11111111111111101110111011001110 .
b11111111111111101110111011001110 2
1$
#240000
0$
#245000
b1111111101111011 ,
b1111010100111 -
b10110 1
b11111111111111101111001100000110 .
b11111111111111101111001100000110 2
1$
#250000
0$
#255000
b1110111 ,
b11101000011011 -
b10111 1
b11111111111111110001000110101101 .
b11111111111111110001000110101101 2
1$
#260000
0$
#265000
b1111111111010101 ,
b110001101110 -
b11000 1
b11111111111111110100101111001000 .
b11111111111111110100101111001000 2
1$
#270000
0$
#275000
b1111111110111110 ,
b1000110001000 -
b11001 1
b11111111111111110101100000110110 .
b11111111111111110101100000110110 2
1$
#280000
0$
#285000
b10001010 ,
b10010100110010 -
b11010 1
b11111111111111110110100110111110 .
b11111111111111110110100110111110 2
1$
#290000
0$
#295000
b1111111101000011 ,
b11111111111111111101001000111010 -
b11011 1
b11111111111111111000111011110000 .
b11111111111111111000111011110000 2
1$
#300000
0$
#305000
b1111111100010110 ,
b1110101000 -
b11100 1
b11111111111111110110000100101010 .
b11111111111111110110000100101010 2
1$
#310000
0$
#315000
b1111111100000100 ,
b11111111111111111010010001110100 -
b11101 1
b11111111111111110110010011010010 .
b11111111111111110110010011010010 2
1$
#320000
0$
#325000
b1001000 ,
b11111111111111111110101011101000 -
b11110 1
b11111111111111110000100101000110 .
b11111111111111110000100101000110 2
1$
#330000
0$
#335000
b10100101 ,
b11111111111111111111100011101001 -
b11111 1
b11111111111111101111010000101110 .
b11111111111111101111010000101110 2
1$
#340000
0$
#345000
b1111111110111000 ,
b11111111111111111110101101111000 -
b100000 1
b11111111111111101110110100010111 .
b11111111111111101110110100010111 2
1$
#350000
0$
#355000
b11000101 ,
b11110011001011 -
b100001 1
b11111111111111101101100010001111 .
b11111111111111101101100010001111 2
1$
#360000
0$
#365000
b10011001 ,
b11111111111111111100101000110110 -
b100010 1
b11111111111111110001010101011010 .
b11111111111111110001010101011010 2
1$
#370000
0$
#375000
b1111111100111001 ,
b11111111111111111011110001011111 -
b100011 1
b11111111111111101101111110010000 .
b11111111111111101101111110010000 2
1$
#380000
0$
#385000
b1111111111100000 ,
b11111111111111111111100010000000 -
b100100 1
b11111111111111101001101111101111 .
b11111111111111101001101111101111 2
1$
#390000
0$
#395000
b1111111100101100 ,
b11111111111111111111101100001000 -
b100101 1
b11111111111111101001010001101111 .
b11111111111111101001010001101111 2
1$
#400000
0$
#405000
b1010111 ,
b1100001111000 -
b100110 1
b11111111111111101000111101110111 .
b11111111111111101000111101110111 2
1$
#410000
0$
#415000
b1111 ,
b11111111111111111111110100010010 -
b100111 1
b11111111111111101010011111101111 .
b11111111111111101010011111101111 2
1$
#420000
0$
#425000
b1111111101000000 ,
b11111111111111111100101011000000 -
b101000 1
b11111111111111101010010100000001 .
b11111111111111101010010100000001 2
1$
#430000
0$
#435000
b1111111100101011 ,
b11010101000 -
b101001 1
b11111111111111100110111111000001 .
b11111111111111100110111111000001 2
1$
#440000
0$
#445000
b1101000 ,
b11111111111111111110110110111000 -
b101010 1
b11111111111111100111011001101001 .
b11111111111111100111011001101001 2
1$
#450000
0$
#455000
b1111111110101101 ,
b11111111111111111111100011011110 -
b101011 1
b11111111111111100110010000100001 .
b11111111111111100110010000100001 2
1$
#460000
0$
#465000
b11001011 ,
b1011111001010 -
b101100 1
b11111111111111100101110011111111 .
b11111111111111100101110011111111 2
1$
#470000
0$
#475000
b11001100 ,
b1100010110100 -
b101101 1
b11111111111111100111010011001001 .
b11111111111111100111010011001001 2
1$
#480000
0$
#485000
b1111111101000010 ,
b11111111111111111010110011100000 -
b101110 1
b11111111111111101000110101111101 .
b11111111111111101000110101111101 2
1$
#490000
0$
#495000
b1111111111011010 ,
b10001001110 -
b101111 1
b11111111111111100011101001011101 .
b11111111111111100011101001011101 2
1$
#500000
0$
#505000
b1111111110001010 ,
b11111111111111111110110110010000 -
b110000 1
b11111111111111100011111010101011 .
b11111111111111100011111010101011 2
1$
#510000
0$
#515000
b1111111110010001 ,
b11111111111111111101110110111111 -
b110001 1
b11111111111111100010110000111011 .
b11111111111111100010110000111011 2
1$
#520000
0$
#525000
b1111111110011001 ,
b10000000110 -
b110010 1
b11111111111111100000100111111010 .
b11111111111111100000100111111010 2
1$
#530000
0$
#535000
b1111111110011011 ,
b101111010110 -
b110011 1
b11111111111111100000111000000000 .
b11111111111111100000111000000000 2
1$
#540000
0$
#545000
b10110111 ,
b11111111111111111100110111110110 -
b110100 1
b11111111111111100001100111010110 .
b11111111111111100001100111010110 2
1$
#550000
0$
#555000
b11011101 ,
b110110011000110 -
b110101 1
b11111111111111011110011111001100 .
b11111111111111011110011111001100 2
1$
#560000
0$
#565000
b1000101 ,
b1001101101000 -
b110110 1
b11111111111111100101010010010010 .
b11111111111111100101010010010010 2
1$
#570000
0$
#575000
b0 ,
b0 -
b110111 1
b11111111111111100110011111111010 .
b11111111111111100110011111111010 2
1$
#580000
0$
#585000
b1101100111000 -
b10000110 ,
b111000 1
1$
#590000
0$
#595000
b1001101 ,
b11111111111111111111101111001010 -
b111001 1
b11111111111111101000001100110010 .
b11111111111111101000001100110010 2
1$
#600000
0$
#605000
b10001000 ,
b11111111111111111101101001001000 -
b111010 1
b11111111111111100111111011111100 .
b11111111111111100111111011111100 2
1$
#610000
0$
#615000
b11111000 ,
b100011110110000 -
b111011 1
b11111111111111100101100101000100 .
b11111111111111100101100101000100 2
1$
#620000
0$
#625000
b1110111 ,
b11101000011011 -
b111100 1
b11111111111111101010000011110100 .
b11111111111111101010000011110100 2
1$
#630000
0$
#635000
b1111111110001010 ,
b1110110000 -
b111101 1
b11111111111111101101101100001111 .
b11111111111111101101101100001111 2
1$
#640000
0$
#645000
b1111111111011101 ,
b11111111111111111111110001110010 -
b111110 1
b11111111111111101101111010111111 .
b11111111111111101101111010111111 2
1$
#650000
0$
#655000
b1111111101000111 ,
b101001111010100 -
b111111 1
b11111111111111101101101100110001 .
b11111111111111101101101100110001 2
1$
#660000
0$
#665000
b11111111 ,
b11111111111111111011101101000101 -
b1000000 1
b11111111111111110010111100000101 .
b11111111111111110010111100000101 2
1$
#670000
0$
#675000
b1111111111001101 ,
b11111111111111111110110100010011 -
b1000001 1
b11111111111111101110101001001010 .
b11111111111111101110101001001010 2
1$
#680000
0$
#685000
b1111111100110000 ,
b10100101110000 -
b1000010 1
b11111111111111101101011101011101 .
b11111111111111101101011101011101 2
1$
#690000
0$
#695000
b1111111111011011 ,
b11010100110 -
b1000011 1
b11111111111111110000000011001101 .
b11111111111111110000000011001101 2
1$
#700000
0$
#705000
b1111111100001010 ,
b11111111111111111000100111001110 -
b1000100 1
b11111111111111110000011101110011 .
b11111111111111110000011101110011 2
1$
#710000
0$
#715000
b1010011 ,
b11111111111111111101100110111110 -
b1000101 1
b11111111111111101001000101000001 .
b11111111111111101001000101000001 2
1$
#720000
0$
#725000
b111110 ,
b110101010010 -
b1000110 1
b11111111111111100110101011111111 .
b11111111111111100110101011111111 2
1$
#730000
0$
#735000
b1011010 ,
b11111111111111111111000100111100 -
b1000111 1
b11111111111111100111100001010001 .
b11111111111111100111100001010001 2
1$
#740000
0$
#745000
b1111111101111010 ,
b11111011010 -
b1001000 1
b11111111111111100110100110001101 .
b11111111111111100110100110001101 2
1$
#750000
0$
#755000
b110011 ,
b100100101010 -
b1001001 1
b11111111111111100111000101100111 .
b11111111111111100111000101100111 2
1$
#760000
0$
#765000
b1111111101100011 ,
b11111111111111111110000010111001 -
b1001010 1
b11111111111111100111101010010001 .
b11111111111111100111101010010001 2
1$
#770000
0$
#775000
b101001 ,
b11111111111111111110111000010000 -
b1001011 1
b11111111111111100101101101001010 .
b11111111111111100101101101001010 2
1$
#780000
0$
#785000
b10010101 ,
b11111111111111111111000011011110 -
b1001100 1
b11111111111111100100100101011010 .
b11111111111111100100100101011010 2
1$
#790000
0$
#795000
b111100 ,
b11111111111111111110010011010000 -
b1001101 1
b11111111111111100011101000111000 .
b11111111111111100011101000111000 2
1$
#800000
0$
#805000
b1101011 ,
b11111111111111111101110011100100 -
b1001110 1
b11111111111111100001111100001000 .
b11111111111111100001111100001000 2
1$
#810000
0$
#815000
b10100 ,
b1111000 -
b1001111 1
b11111111111111011111101111101100 .
b11111111111111011111101111101100 2
1$
#820000
0$
#825000
b10111111 ,
b11111111111111111011010101100100 -
b1010000 1
b11111111111111011111110001100100 .
b11111111111111011111110001100100 2
1$
#830000
0$
#835000
b1111111101111010 ,
b101001111000 -
b1010001 1
b11111111111111011011000111001000 .
b11111111111111011011000111001000 2
1$
#840000
0$
#845000
b11000 ,
b1011010000 -
b1010010 1
b11111111111111011011110001000000 .
b11111111111111011011110001000000 2
1$
#850000
0$
#855000
b1100 ,
b10001000100 -
b1010011 1
b11111111111111011011111100010000 .
b11111111111111011011111100010000 2
1$
#860000
0$
#865000
b1111111111110010 ,
b11111111111111111111110110100110 -
b1010100 1
b11111111111111011100001101010100 .
b11111111111111011100001101010100 2
1$
#870000
0$
#875000
b1111111111100010 ,
b100001110 -
b1010101 1
b11111111111111011100000011111010 .
b11111111111111011100000011111010 2
1$
#880000
0$
#885000
b110101 ,
b111011101 -
b1010110 1
b11111111111111011100001000001000 .
b11111111111111011100001000001000 2
1$
#890000
0$
#895000
b1111111100000111 ,
b100110111010000 -
b1010111 1
b11111111111111011100001111100101 .
b11111111111111011100001111100101 2
1$
#900000
0$
#905000
b11101010 ,
b11111111111111111000111010101000 -
b1011000 1
b11111111111111100001000110110101 .
b11111111111111100001000110110101 2
1$
#910000
0$
#915000
b100101 ,
b11111111111111111111010010111010 -
b1011001 1
b11111111111111011010000001011101 .
b11111111111111011010000001011101 2
1$
#920000
0$
#925000
b11100100 ,
b11111111111111111011011011111000 -
b1011010 1
b11111111111111011001010100010111 .
b11111111111111011001010100010111 2
1$
#930000
0$
#935000
b1111111111001010 ,
b1011111010110 -
b1011011 1
b11111111111111010100110000001111 .
b11111111111111010100110000001111 2
1$
#940000
0$
#945000
b1111111101010001 ,
b11111111111111111011010000011111 -
b1011100 1
b11111111111111010110001111100101 .
b11111111111111010110001111100101 2
1$
#950000
0$
#955000
b1111111101010011 ,
b100110100001010 -
b1011101 1
b11111111111111010001100000000100 .
b11111111111111010001100000000100 2
1$
#960000
0$
#965000
b1111111100010111 ,
b11111111111111111111000101110000 -
b1011110 1
b11111111111111010110010100001110 .
b11111111111111010110010100001110 2
1$
#970000
0$
#975000
b1111111101110101 ,
b11111111111111111011111101100011 -
b1011111 1
b11111111111111010101011001111110 .
b11111111111111010101011001111110 2
1$
#980000
0$
#985000
b10001000 ,
b11111111111111111111010011011000 -
b1100000 1
b11111111111111010001010111100001 .
b11111111111111010001010111100001 2
1$
#990000
0$
#995000
b11000000 ,
b11111111111111111011001000000000 -
b1100001 1
b11111111111111010000101010111001 .
b11111111111111010000101010111001 2
1$
#1000000
0$
#1005000
b1111111111000100 ,
b1100001100 -
b1100010 1
b11111111111111001011110010111001 .
b11111111111111001011110010111001 2
1$
#1010000
0$
#1015000
b1111111110110111 ,
b11101101010 -
b1100011 1
b11111111111111001011111111000101 .
b11111111111111001011111111000101 2
1$
#1020000
0$
#1025000
b1111111110111110 ,
b11111111111111111111110010100110 -
b1100100 1
b11111111111111001100011100101111 .
b11111111111111001100011100101111 2
1$
#1030000
0$
#1035000
b11100011 ,
b11111111111111111010101111000011 -
b1100101 1
b11111111111111001100001111010101 .
b11111111111111001100001111010101 2
1$
#1040000
0$
#1045000
b1111111101000100 ,
b100011010000 -
b1100110 1
b11111111111111000110111110011000 .
b11111111111111000110111110011000 2
1$
#1050000
0$
#1055000
b111000 ,
b10101000000 -
b1100111 1
b11111111111111000111100001101000 .
b11111111111111000111100001101000 2
1$
#1060000
0$
#1065000
b1101111 ,
b11111111111111111110010100011110 -
b1101000 1
b11111111111111000111110110101000 .
b11111111111111000111110110101000 2
1$
#1070000
0$
#1075000
b1111111 ,
b10010110110100 -
b1101001 1
b11111111111111000110001011000110 .
b11111111111111000110001011000110 2
1$
#1080000
0$
#1085000
b111 ,
b11111111111111111111111101011111 -
b1101010 1
b11111111111111001000100001111010 .
b11111111111111001000100001111010 2
1$
#1090000
0$
#1095000
b1111111110010100 ,
b10000111000000 -
b1101011 1
b11111111111111001000011111011001 .
b11111111111111001000011111011001 2
1$
#1100000
0$
#1105000
b1111111111001101 ,
b11111111111111111111110100000011 -
b1101100 1
b11111111111111001010100110011001 .
b11111111111111001010100110011001 2
1$
#1110000
0$
#1115000
b1111111111000000 ,
b110000000 -
b1101101 1
b11111111111111001010011010011100 .
b11111111111111001010011010011100 2
1$
#1120000
0$
#1125000
b110000 ,
b11111111111111111111000111000000 -
b1101110 1
b11111111111111001010100000011100 .
b11111111111111001010100000011100 2
1$
#1130000
0$
#1135000
b1111111100110001 ,
b11111111111111111111100010111001 -
b1101111 1
b11111111111111001001100111011100 .
b11111111111111001001100111011100 2
1$
#1140000
0$
#1145000
b1111111110110001 ,
b10000100000101 -
b1110000 1
b11111111111111001001001010010101 .
b11111111111111001001001010010101 2
1$
#1150000
0$
#1155000
b1111111110011010 ,
b1011001010000 -
b1110001 1
b11111111111111001011001110011010 .
b11111111111111001011001110011010 2
1$
#1160000
0$
#1165000
b1111111111000001 ,
b1011110100 -
b1110010 1
b11111111111111001100100111101010 .
b11111111111111001100100111101010 2
1$
#1170000
0$
#1175000
b11101101 ,
b11111111111111111100101100111011 -
b1110011 1
b11111111111111001100110011011110 .
b11111111111111001100110011011110 2
1$
#1180000
0$
#1185000
b1111111101001111 ,
b11110110001001 -
b1110100 1
b11111111111111001001100000011001 .
b11111111111111001001100000011001 2
1$
#1190000
0$
#1195000
b1111111111111100 ,
b11111111111111111111111000011100 -
b1110101 1
b11111111111111001101010110100010 .
b11111111111111001101010110100010 2
1$
#1200000
0$
#1205000
b1111111110000000 ,
b11010010000000 -
b1110110 1
b11111111111111001101001110111110 .
b11111111111111001101001110111110 2
1$
#1210000
0$
#1215000
b1111111111111010 ,
b11111111111111111111111000110010 -
b1110111 1
b11111111111111010000100000111110 .
b11111111111111010000100000111110 2
1$
#1220000
0$
#1225000
b11100101 ,
b100111010111000 -
b1111000 1
b11111111111111010000011001110000 .
b11111111111111010000011001110000 2
1$
#1230000
0$
#1235000
b11010111 ,
b11010111000000 -
b1111001 1
b11111111111111010101010100101000 .
b11111111111111010101010100101000 2
1$
#1240000
0$
#1245000
b1111111111111011 ,
b11111111111111111111111001110000 -
b1111010 1
b11111111111111011000101011101000 .
b11111111111111011000101011101000 2
1$
#1250000
0$
