Willthon/GAN_test/layer3_discriminator.v
module layer3_discriminator (
    input wire clk,
    input wire rst,
    input wire start,
    // Flattened input bus: 32 elements * 16 bits = 512 bits
    input wire signed [16*32-1:0] flat_input_flat,
    // Output: single 16-bit score (final decision)
    output reg signed [15:0] score_out,
    output reg decision_real,
    output reg done
);

    // ==========================================
    // Memory untuk Parameter (Weights & Biases)
    // ==========================================
    // Total weights: 1 neuron * 32 input = 32
    reg signed [15:0] layer3_disc_weights [0:31]; 
    reg signed [15:0] layer3_disc_bias  [0:0];

    initial begin
        // Load data hex dari hex_data directory (expanded format)
        $readmemh("hex_data/Discriminator_Layer3_Weights_All.hex", layer3_disc_weights);
        $readmemh("hex_data/Discriminator_Layer3_Biases_All.hex", layer3_disc_bias);
    end

    // ==========================================
    // Sequential MAC Pipeline State
    // ==========================================
    // Single neuron, 32 inputs
    // Inner loop: input index (0..31)
    reg [5:0] input_idx;    // 0..31
    reg busy;
    reg signed [31:0] accumulator;
    reg signed [31:0] bias_shifted;

    // Combinational wires for current input and product
    wire signed [15:0] current_input;
    wire signed [31:0] current_product;
    wire signed [31:0] next_acc;

    assign current_input = $signed(flat_input_flat[(input_idx+1)*16-1 -: 16]);
    assign current_product = $signed(current_input) * $signed(layer3_disc_weights[input_idx]);
    assign next_acc = accumulator + current_product;

    // Sequential MAC pipeline: one MAC operation per clock cycle
    always @(posedge clk or posedge rst) begin
        if (rst) begin
            input_idx <= 6'd0;
            accumulator <= 32'sd0;
            bias_shifted <= 32'sd0;
            busy <= 1'b0;
            done <= 1'b0;
            score_out <= 16'sd0;
            decision_real <= 1'b0;
        end else begin
            if (start && !busy) begin
                // Start a new computation: begin with input 0, load bias
                input_idx <= 6'd0;
                bias_shifted <= $signed(layer3_disc_bias[0]) <<< 8;
                accumulator <= $signed(layer3_disc_bias[0]) <<< 8;
                busy <= 1'b1;
                done <= 1'b0;
            end else if (busy) begin
                // Perform one MAC: accumulator += input[input_idx] * weight[input_idx]
                accumulator <= next_acc;

                if (input_idx == 6'd31) begin
                    // Finished all 32 inputs; write output and finish
                    score_out <= next_acc[23:8]; // scale Q16.16 -> Q8.8
                    decision_real <= (next_acc > 0) ? 1'b1 : 1'b0; // decision threshold at 0
                    busy <= 1'b0;
                    done <= 1'b1;
                end else begin
                    // Continue with next input
                    input_idx <= input_idx + 1'b1;
                end
            end else begin
                // idle: clear done after one cycle so user can pulse start again
                if (done)
                    done <= 1'b0;
            end
        end
    end

endmodule

Willthon/GAN_test/layer3_discriminator_tb.v
`timescale 1ns / 1ps

module layer3_discriminator_tb;

    // Inputs: 32 elements (from Discriminator layer 2 output)
    reg signed [15:0] inputs [0:31];
    reg signed [16*32-1:0] flat_input;
    reg clk;
    reg rst;
    reg start;

    // Outputs: single decision + score
    wire signed [15:0] score_out;
    wire decision_real;
    wire done;

    // Instantiate Unit Under Test (UUT)
    layer3_discriminator uut (
        .clk(clk),
        .rst(rst),
        .start(start),
        .flat_input_flat(flat_input),
        .score_out(score_out),
        .decision_real(decision_real),
        .done(done)
    );

    // Keep the flattened bus updated
    integer i_pack;
    always @(*) begin
        for (i_pack = 0; i_pack < 32; i_pack = i_pack + 1) begin
            flat_input[(i_pack+1)*16-1 -: 16] = inputs[i_pack];
        end
    end

    // Helper to convert Q8.8 to real
    function real q8_8_to_real;
        input signed [15:0] val;
        begin
            q8_8_to_real = val / 256.0;
        end
    endfunction

    integer k;

    // Clock generator: 10ns period (100 MHz)
    initial begin
        clk = 0;
        forever #5 clk = ~clk;
    end

    initial begin
        $dumpfile("discriminator_layer3_test.vcd");
        $dumpvars(0, layer3_discriminator_tb);

        // Reset
        rst = 1;
        start = 0;
        #20;
        rst = 0;

        // Initialize inputs to zero
        for (k = 0; k < 32; k = k + 1) begin
            inputs[k] = 16'sd0;
        end

        $display("--------------------------------------------------");
        $display("   TESTING DISCRIMINATOR LAYER 3 (FINAL)");
        $display("   32 inputs -> 1 output (REAL/FAKE decision)");
        $display("--------------------------------------------------");

        // Test Case 1: Zero inputs (output should be bias only)
        $display("\nTest Case 1: Zero Inputs");
        for (k = 0; k < 32; k = k + 1) begin
            inputs[k] = 16'sd0;
        end

        @(posedge clk);
        start = 1;
        @(posedge clk);
        start = 0;

        wait(done == 1);
        #1;

        $display("Output Score (zero input): %f (hex: %h)", 
                 q8_8_to_real(score_out),
                 score_out);
        $display("Decision: %b (1=REAL, 0=FAKE)", decision_real);

        // Test Case 2: Small random inputs
        $display("\nTest Case 2: Random Inputs");
        for (k = 0; k < 32; k = k + 1) begin
            inputs[k] = $random % 256;
        end

        @(posedge clk);
        start = 1;
        @(posedge clk);
        start = 0;

        wait(done == 1);
        #1;

        $display("Output Score (random input): %f (hex: %h)", 
                 q8_8_to_real(score_out),
                 score_out);
        $display("Decision: %b (1=REAL, 0=FAKE)", decision_real);

        // Test Case 3: Positive bias (should favor REAL)
        $display("\nTest Case 3: Large Positive Inputs");
        for (k = 0; k < 32; k = k + 1) begin
            inputs[k] = 16'sd100; // 100/256 ≈ 0.39
        end

        @(posedge clk);
        start = 1;
        @(posedge clk);
        start = 0;

        wait(done == 1);
        #1;

        $display("Output Score (positive input): %f (hex: %h)", 
                 q8_8_to_real(score_out),
                 score_out);
        $display("Decision: %b (1=REAL, 0=FAKE)", decision_real);

        $display("--------------------------------------------------");
        $display("Layer 3 Test Complete");
        $display("--------------------------------------------------");

        $finish;
    end

endmodule

Willthon/GAN_test/discriminator_layer3_test.vcd
$date
	Sat Nov 29 20:48:30 2025
$end
$version
	Icarus Verilog
$end
$timescale
	1ps
$end
$scope module layer3_discriminator_tb $end
$var wire 16 ! score_out [15:0] $end
$var wire 1 " done $end
$var wire 1 # decision_real $end
$var reg 1 $ clk $end
$var reg 512 % flat_input [511:0] $end
$var reg 1 & rst $end
$var reg 1 ' start $end
$var integer 32 ( i_pack [31:0] $end
$var integer 32 ) k [31:0] $end
$scope function q8_8_to_real $end
$var reg 16 * val [15:0] $end
$upscope $end
$scope module uut $end
$var wire 1 $ clk $end
$var wire 512 + flat_input_flat [511:0] $end
$var wire 1 & rst $end
$var wire 1 ' start $end
$var wire 32 , next_acc [31:0] $end
$var wire 32 - current_product [31:0] $end
$var wire 16 . current_input [15:0] $end
$var reg 32 / accumulator [31:0] $end
$var reg 32 0 bias_shifted [31:0] $end
$var reg 1 1 busy $end
$var reg 1 # decision_real $end
$var reg 1 " done $end
$var reg 6 2 input_idx [5:0] $end
$var reg 16 3 score_out [15:0] $end
$upscope $end
$upscope $end
$enddefinitions $end
$comment Show the parameter values. $end
$dumpall
$end
#0
$dumpvars
b0 3
b0 2
01
b0 0
b0 /
bx .
bx -
bx ,
bx +
bx *
bx )
bx (
0'
1&
bx %
0$
0#
0"
b0 !
$end
#5000
1$
#10000
0$
#15000
1$
#20000
b0 ,
b0 -
b0 .
b0 %
b0 +
b100000 (
0$
b100000 )
0&
#25000
11
b11111111111111100111010000000000 ,
b11111111111111100111010000000000 /
b11111111111111100111010000000000 0
1'
1$
#30000
0$
#35000
b1 2
0'
1$
#40000
0$
#45000
b10 2
1$
#50000
0$
#55000
b11 2
1$
#60000
0$
#65000
b100 2
1$
#70000
0$
#75000
b101 2
1$
#80000
0$
#85000
b110 2
1$
#90000
0$
#95000
b111 2
1$
#100000
0$
#105000
b1000 2
1$
#110000
0$
#115000
b1001 2
1$
#120000
0$
#125000
b1010 2
1$
#130000
0$
#135000
b1011 2
1$
#140000
0$
#145000
b1100 2
1$
#150000
0$
#155000
b1101 2
1$
#160000
0$
#165000
b1110 2
1$
#170000
0$
#175000
b1111 2
1$
#180000
0$
#185000
b10000 2
1$
#190000
0$
#195000
b10001 2
1$
#200000
0$
#205000
b10010 2
1$
#210000
0$
#215000
b10011 2
1$
#220000
0$
#225000
b10100 2
1$
#230000
0$
#235000
b10101 2
1$
#240000
0$
#245000
b10110 2
1$
#250000
0$
#255000
b10111 2
1$
#260000
0$
#265000
b11000 2
1$
#270000
0$
#275000
b11001 2
1$
#280000
0$
#285000
b11010 2
1$
#290000
0$
#295000
b11011 2
1$
#300000
0$
#305000
b11100 2
1$
#310000
0$
#315000
b11101 2
1$
#320000
0$
#325000
b11110 2
1$
#330000
0$
#335000
b11111 2
1$
#340000
0$
#345000
1"
01
b1111111001110100 !
b1111111001110100 3
1$
#346000
b11111111111111100111010101011110 ,
b101011110 -
b1010 .
b10101111111101100011111111110110010111111111001011011111111110111101000000000101110011111111110001011111111111101000111111111100111000000000111100100000000010001111111111110001001011111111011101110000000011100101111111111010101011111111110001011111111111000110000000001111100100000000100011000000000011101101000000000011110100000000011101100000000000001101000000000000000111111111000100101111111101100101000000001000110100000000000011011111111101100011111111110000100111111111100000010000000000100100 %
b10101111111101100011111111110110010111111111001011011111111110111101000000000101110011111111110001011111111111101000111111111100111000000000111100100000000010001111111111110001001011111111011101110000000011100101111111111010101011111111110001011111111111000110000000001111100100000000100011000000000011101101000000000011110100000000011101100000000000001101000000000000000111111111000100101111111101100101000000001000110100000000000011011111111101100011111111110000100111111111100000010000000000100100 +
b100000 (
b100000 )
b1111111001110100 *
#350000
0$
#355000
0"
11
b100100 .
b11111111111111100110111100111000 ,
b11111111111111111111101100111000 -
b0 2
1'
1$
#360000
0$
#365000
b1111111110000001 .
b11111111111111111110000110111101 -
b1 2
b11111111111111100101000011110101 ,
b11111111111111100110111100111000 /
0'
1$
#370000
0$
#375000
b11111111111111111100010100100101 -
b1111111100001001 .
b10 2
b11111111111111100001011000011010 ,
b11111111111111100101000011110101 /
1$
#380000
0$
#385000
b1111111101100011 .
b11111111111111111110101100100110 -
b11 2
b11111111111111100000000101000000 ,
b11111111111111100001011000011010 /
1$
#390000
0$
#395000
b1101 .
b11111111111111111111110111111000 -
b100 2
b11111111111111011111111100111000 ,
b11111111111111100000000101000000 /
1$
#400000
0$
#405000
b10001101 .
b11111111111111111110010100000011 -
b101 2
b11111111111111011110010000111011 ,
b11111111111111011111111100111000 /
1$
#410000
0$
#415000
b1111111101100101 .
b11111111111111111110111001110001 -
b110 2
b11111111111111011101001010101100 ,
b11111111111111011110010000111011 /
1$
#420000
0$
#425000
b1111111100010010 .
b10011111111010 -
b111 2
b11111111111111011111101010100110 ,
b11111111111111011101001010101100 /
1$
#430000
0$
#435000
b1 .
b11111111111111111111111111011010 -
b1000 2
b11111111111111011111101010000000 ,
b11111111111111011111101010100110 /
1$
#440000
0$
#445000
b1101 .
b111010100 -
b1001 2
b11111111111111011111110001010100 ,
b11111111111111011111101010000000 /
1$
#450000
0$
#455000
b1110110 .
b10000100110000 -
b1010 2
b11111111111111100001110110000100 ,
b11111111111111011111110001010100 /
1$
#460000
0$
#465000
b111101 .
b11111111111111111111010111111110 -
b1011 2
b11111111111111100001001110000010 ,
b11111111111111100001110110000100 /
1$
#470000
0$
#475000
b11101101 .
b11111111111111111101101111100101 -
b1100 2
b11111111111111011110111101100111 ,
b11111111111111100001001110000010 /
1$
#480000
0$
#485000
b10001100 .
b11111111111111111110011011011000 -
b1101 2
b11111111111111011101011000111111 ,
b11111111111111011110111101100111 /
1$
#490000
0$
#495000
b11111001 .
b11010010000110 -
b1110 2
b11111111111111100000101011000101 ,
b11111111111111011101011000111111 /
1$
#500000
0$
#505000
b1111111111000110 .
b11111111111111111111100011000000 -
b1111 2
b11111111111111100000001110000101 ,
b11111111111111100000101011000101 /
1$
#510000
0$
#515000
b1111111111000101 .
b11111111111111111111001101010011 -
b10000 2
b11111111111111011111011011011000 ,
b11111111111111100000001110000101 /
1$
#520000
0$
#525000
b1111111110101010 .
b110101110000 -
b10001 2
b11111111111111100000010001001000 ,
b11111111111111011111011011011000 /
1$
#530000
0$
#535000
b11100101 .
b11111111111111111101110100011101 -
b10010 2
b11111111111111011110000101100101 ,
b11111111111111100000010001001000 /
1$
#540000
0$
#545000
b1111111101110111 .
b110101100001 -
b10011 2
b11111111111111011110111011000110 ,
b11111111111111011110000101100101 /
1$
#550000
0$
#555000
b1111111100010010 .
b11000101000110 -
b10100 2
b11111111111111100010000000001100 ,
b11111111111111011110111011000110 /
1$
#560000
0$
#565000
b10001111 .
b11111111111111111110111111001101 -
b10101 2
b11111111111111100000111111011001 ,
b11111111111111100010000000001100 /
1$
#570000
0$
#575000
b11110010 .
b11111111111111111100010001110010 -
b10110 2
b11111111111111011101010001001011 ,
b11111111111111100000111111011001 /
1$
#580000
0$
#585000
b1111111111001110 .
b11111111111111111111011101101000 -
b10111 2
b11111111111111011100101110110011 ,
b11111111111111011101010001001011 /
1$
#590000
0$
#595000
b1111111111101000 .
b11111111111111111111101011110000 -
b11000 2
b11111111111111011100011010100011 ,
b11111111111111011100101110110011 /
1$
#600000
0$
#605000
b1111111111000101 .
b100111101001 -
b11001 2
b11111111111111011101000010001100 ,
b11111111111111011100011010100011 /
1$
#610000
0$
#615000
b1011100 .
b1010011011000 -
b11010 2
b11111111111111011110010101100100 ,
b11111111111111011101000010001100 /
1$
#620000
0$
#625000
b1111111110111101 .
b11111111111111111111000100010101 -
b11011 2
b11111111111111011101011001111001 ,
b11111111111111011110010101100100 /
1$
#630000
0$
#635000
b1111111100101101 .
b11111111111111111110100110111111 -
b11100 2
b11111111111111011100000000111000 ,
b11111111111111011101011001111001 /
1$
#640000
0$
#645000
b1111111101100101 .
b11111111111111111110001001010101 -
b11101 2
b11111111111111011010001010001101 ,
b11111111111111011100000000111000 /
1$
#650000
0$
#655000
b1111111101100011 .
b1011010110001 -
b11110 2
b11111111111111011011100100111110 ,
b11111111111111011010001010001101 /
1$
#660000
0$
#665000
b1010 .
b101011110 -
b11111 2
b11111111111111011011101010011100 ,
b11111111111111011011100100111110 /
1$
#670000
0$
#675000
1"
01
b1111110110111010 !
b1111110110111010 3
b11111111111111011011101111111010 ,
b11111111111111011011101010011100 /
1$
#676000
b11111111111111011100100001001000 ,
b110110101100 -
b1100100 .
b11001000000000001100100000000000110010000000000011001000000000001100100000000000110010000000000011001000000000001100100000000000110010000000000011001000000000001100100000000000110010000000000011001000000000001100100000000000110010000000000011001000000000001100100000000000110010000000000011001000000000001100100000000000110010000000000011001000000000001100100000000000110010000000000011001000000000001100100000000000110010000000000011001000000000001100100000000000110010000000000011001000000000001100100 %
b11001000000000001100100000000000110010000000000011001000000000001100100000000000110010000000000011001000000000001100100000000000110010000000000011001000000000001100100000000000110010000000000011001000000000001100100000000000110010000000000011001000000000001100100000000000110010000000000011001000000000001100100000000000110010000000000011001000000000001100100000000000110010000000000011001000000000001100100000000000110010000000000011001000000000001100100000000000110010000000000011001000000000001100100 +
b100000 (
b100000 )
b1111110110111010 *
#680000
0$
#685000
0"
11
b11111111111111100111010000000000 /
b11111111111111100110011010111000 ,
b11111111111111111111001010111000 -
b0 2
1'
1$
#690000
0$
#695000
b1011111010100 -
b1 2
b11111111111111100111111010001100 ,
b11111111111111100110011010111000 /
0'
1$
#700000
0$
#705000
b10 2
b11111111111111101001011001100000 ,
b11111111111111100111111010001100 /
1$
#710000
0$
#715000
b110101001000 -
b11 2
b11111111111111101010001110101000 ,
b11111111111111101001011001100000 /
1$
#720000
0$
#725000
b11111111111111111111000001100000 -
b100 2
b11111111111111101001010000001000 ,
b11111111111111101010001110101000 /
1$
#730000
0$
#735000
b11111111111111111110110011011100 -
b101 2
b11111111111111101000000011100100 ,
b11111111111111101001010000001000 /
1$
#740000
0$
#745000
b101101010100 -
b110 2
b11111111111111101000110000111000 ,
b11111111111111101000000011100100 /
1$
#750000
0$
#755000
b11111111111111111110111100110100 -
b111 2
b11111111111111100111101101101100 ,
b11111111111111101000110000111000 /
1$
#760000
0$
#765000
b11111111111111111111000100101000 -
b1000 2
b11111111111111100110110010010100 ,
b11111111111111100111101101101100 /
1$
#770000
0$
#775000
b111000010000 -
b1001 2
b11111111111111100111101010100100 ,
b11111111111111100110110010010100 /
1$
#780000
0$
#785000
b1110000100000 -
b1010 2
b11111111111111101001011011000100 ,
b11111111111111100111101010100100 /
1$
#790000
0$
#795000
b11111111111111111110111110011000 -
b1011 2
b11111111111111101000011001011100 ,
b11111111111111101001011011000100 /
1$
#800000
0$
#805000
b11111111111111111111000011000100 -
b1100 2
b11111111111111100111011100100000 ,
b11111111111111101000011001011100 /
1$
#810000
0$
#815000
b11111111111111111110111000001000 -
b1101 2
b11111111111111100110010100101000 ,
b11111111111111100111011100100000 /
1$
#820000
0$
#825000
b1010100011000 -
b1110 2
b11111111111111100111101001000000 ,
b11111111111111100110010100101000 /
1$
#830000
0$
#835000
b110010000000 -
b1111 2
b11111111111111101000011011000000 ,
b11111111111111100111101001000000 /
1$
#840000
0$
#845000
b1010101111100 -
b10000 2
b11111111111111101001110000111100 ,
b11111111111111101000011011000000 /
1$
#850000
0$
#855000
b11111111111111111111000001100000 -
b10001 2
b11111111111111101000110010011100 ,
b11111111111111101001110000111100 /
1$
#860000
0$
#865000
b11111111111111111111000011000100 -
b10010 2
b11111111111111100111110101100000 ,
b11111111111111101000110010011100 /
1$
#870000
0$
#875000
b11111111111111111111011000111100 -
b10011 2
b11111111111111100111001110011100 ,
b11111111111111100111110101100000 /
1$
#880000
0$
#885000
b11111111111111111110101101001100 -
b10100 2
b11111111111111100101111011101000 ,
b11111111111111100111001110011100 /
1$
#890000
0$
#895000
b11111111111111111111010010101100 -
b10101 2
b11111111111111100101001110010100 ,
b11111111111111100101111011101000 /
1$
#900000
0$
#905000
b11111111111111111110011101100100 -
b10110 2
b11111111111111100011101011111000 ,
b11111111111111100101001110010100 /
1$
#910000
0$
#915000
b1000100110000 -
b10111 2
b11111111111111100100110000101000 ,
b11111111111111100011101011111000 /
1$
#920000
0$
#925000
b1010100011000 -
b11000 2
b11111111111111100110000101000000 ,
b11111111111111100100110000101000 /
1$
#930000
0$
#935000
b11111111111111111110111100110100 -
b11001 2
b11111111111111100101000001110100 ,
b11111111111111100110000101000000 /
1$
#940000
0$
#945000
b1011010101000 -
b11010 2
b11111111111111100110011100011100 ,
b11111111111111100101000001110100 /
1$
#950000
0$
#955000
b1011001000100 -
b11011 2
b11111111111111100111110101100000 ,
b11111111111111100110011100011100 /
1$
#960000
0$
#965000
b101010001100 -
b11100 2
b11111111111111101000011111101100 ,
b11111111111111100111110101100000 /
1$
#970000
0$
#975000
b1001100100100 -
b11101 2
b11111111111111101001101100010000 ,
b11111111111111101000011111101100 /
1$
#980000
0$
#985000
b11111111111111111111000110001100 -
b11110 2
b11111111111111101000110010011100 ,
b11111111111111101001101100010000 /
1$
#990000
0$
#995000
b110110101100 -
b11111 2
b11111111111111101001101001001000 ,
b11111111111111101000110010011100 /
1$
#1000000
0$
#1005000
1"
01
b1111111010011010 !
b1111111010011010 3
b11111111111111101010011111110100 ,
b11111111111111101001101001001000 /
1$
#1006000
b1111111010011010 *
